c2dataviewer/__init__.py
c2dataviewer/c2dv.cfg
c2dataviewer/c2dv.py
c2dataviewer/imagev.py
c2dataviewer/scope.py
c2dataviewer/striptool.py
c2dataviewer/control/__init__.py
c2dataviewer/control/config.py
c2dataviewer/control/imagecontroller.py
c2dataviewer/control/pvconfig.py
c2dataviewer/control/pvedit_dialog_controller.py
c2dataviewer/control/scope_config_base.py
c2dataviewer/control/scope_controller_base.py
c2dataviewer/control/scopeconfig.py
c2dataviewer/control/scopecontroller.py
c2dataviewer/control/striptool_controller.py
c2dataviewer/control/striptoolconfig.py
c2dataviewer/model/__init__.py
c2dataviewer/model/pvapy_plugins.py
c2dataviewer/ui/__init__.py
c2dataviewer/ui/action.ui
c2dataviewer/ui/addpv.ui
c2dataviewer/ui/imagev.ui
c2dataviewer/ui/imagev_settings.ui
c2dataviewer/ui/scope.ui
c2dataviewer/ui/striptool.ui
c2dataviewer/ui/warning.ui
c2dataviewer/view/__init__.py
c2dataviewer/view/image_definitions.py
c2dataviewer/view/image_display.py
c2dataviewer/view/image_profile_display.py
c2dataviewer/view/scope_display.py
c2dataviewer/view/ui_components.py
c2dataviewer-1.15.4.dist-info/licenses/LICENSE
test/__init__.py
test/helper.py
test/test_image_definitions.py
test/test_image_display.py
test/test_image_profile_display.py
test/test_imagecontroller.py
test/test_imagev.py
test/test_scope_config.py
test/test_scope_display.py
test/test_scopecontroller.py
test/test_striptool_config.py
test/test_striptool_controller.py
c2dataviewer-1.15.4.dist-info/METADATA
c2dataviewer-1.15.4.dist-info/WHEEL
c2dataviewer-1.15.4.dist-info/entry_points.txt
c2dataviewer-1.15.4.dist-info/top_level.txt
c2dataviewer-1.15.4.dist-info/RECORD
