Metadata-Version: 2.4
Name: c2dataviewer
Version: 1.15.4
Summary: Python based data viewer for next generation of APS control system (C2)
Home-page: https://github.com/epics-extensions/c2dataviewer
Author: G. Shen
Author-email: gshen@anl.gov
License: EPICS
License-File: LICENSE
Requires-Dist: psutil
Requires-Dist: pvapy
Requires-Dist: pyqtgraph==0.13
Requires-Dist: PyQt5
Provides-Extra: blosc-compression
Requires-Dist: blosc; extra == "blosc-compression"
Provides-Extra: lz4-compression
Requires-Dist: lz4; extra == "lz4-compression"
Provides-Extra: bslz4-compression
Requires-Dist: bitshuffle; extra == "bslz4-compression"
Provides-Extra: all
Requires-Dist: blosc; extra == "all"
Requires-Dist: lz4; extra == "all"
Requires-Dist: bitshuffle; extra == "all"
Dynamic: author
Dynamic: author-email
Dynamic: description
Dynamic: description-content-type
Dynamic: home-page
Dynamic: license
Dynamic: license-file
Dynamic: provides-extra
Dynamic: requires-dist
Dynamic: summary
